sopel_8ball/__init__.py
sopel_8ball/choices.py
sopel_8ball/config.py
sopel_8ball/managers.py
sopel_8ball/plugin.py
sopel_8ball-0.5.0.dist-info/LICENSE.txt
sopel_8ball-0.5.0.dist-info/METADATA
sopel_8ball-0.5.0.dist-info/WHEEL
sopel_8ball-0.5.0.dist-info/entry_points.txt
sopel_8ball-0.5.0.dist-info/top_level.txt
sopel_8ball-0.5.0.dist-info/RECORD
