Metadata-Version: 2.1
Name: sopel-8ball
Version: 0.5.0
Summary: Magic 8 ball plugin for Sopel
Author-email: dgw <dgw@technobabbl.es>, Florian Strzelecki <florian.strzelecki@gmail.com>
Maintainer-email: Florian Strzelecki <florian.strzelecki@gmail.com>
License: EFL-2.0
Project-URL: Homepage, https://github.com/Exirel/sopel-8ball
Project-URL: Bug Tracker, https://github.com/Exirel/sopel-8ball/issues
Keywords: sopel,plugin,height-ball,bot,irc
Platform: Linux x86, x86-64
Classifier: Development Status :: 4 - Beta
Classifier: Intended Audience :: Developers
Classifier: Intended Audience :: System Administrators
Classifier: License :: Eiffel Forum License (EFL)
Classifier: License :: OSI Approved :: Eiffel Forum License
Classifier: Operating System :: POSIX :: Linux
Classifier: Programming Language :: Python :: 3.6
Classifier: Programming Language :: Python :: 3.7
Classifier: Programming Language :: Python :: 3.8
Classifier: Programming Language :: Python :: 3.9
Classifier: Programming Language :: Python :: 3.10
Classifier: Topic :: Communications :: Chat :: Internet Relay Chat
Requires-Python: <4,>=3.6
License-File: LICENSE.txt
Requires-Dist: sopel >=7.1
